{
  "version": "2.2.0",
  "summary": {
    "title": "URL shortener",
    "owner": "",
    "description": "The URL Shortener Service aims to provide a simple and efficient way for users to convert long URLs into short, easily shareable URLs. The service ensures functionality, reliability, and security while interacting with users and handling their data.",
    "id": 0
  },
  "detail": {
    "contributors": [],
    "diagrams": [
      {
        "id": 0,
        "title": "URL Shortener Service Architecture",
        "diagramType": "STRIDE",
        "placeholder": "New STRIDE diagram description",
        "thumbnail": "./public/content/images/thumbnail.stride.jpg",
        "version": "2.2.0",
        "cells": [
          {
            "position": {
              "x": 410,
              "y": 60
            },
            "size": {
              "width": 690,
              "height": 370
            },
            "shape": "trust-boundary-box",
            "attrs": {
              "headerText": {
                "text": "URL Shortener Service"
              }
            },
            "zIndex": -1,
            "id": "b830597f-432f-4c75-a688-8722ce7f1585",
            "data": {
              "type": "tm.BoundaryBox",
              "name": "URL Shortener Service",
              "description": "URL Shortener Service trust boundary",
              "isTrustBoundary": true,
              "hasOpenThreats": false
            }
          },
          {
            "position": {
              "x": 190,
              "y": 147
            },
            "size": {
              "width": 170,
              "height": 90
            },
            "attrs": {
              "text": {
                "text": "Human User / Service"
              },
              "body": {
                "stroke": "#333333",
                "strokeWidth": 1.5,
                "strokeDasharray": "4 3"
              }
            },
            "visible": true,
            "shape": "actor",
            "zIndex": 2,
            "id": "3ebe0ef2-2820-4e4d-8eb4-184714e6cf67",
            "data": {
              "type": "tm.Actor",
              "name": "Human User / Service",
              "description": "External services or human users may interact with the API for bulk operations or integrations.",
              "outOfScope": true,
              "reasonOutOfScope": "Incoming requests outside of application scope",
              "hasOpenThreats": false,
              "providesAuthentication": false,
              "threats": []
            }
          },
          {
            "position": {
              "x": 750,
              "y": 290
            },
            "size": {
              "width": 100,
              "height": 100
            },
            "attrs": {
              "text": {
                "text": "Redirect URL"
              },
              "body": {
                "stroke": "#333333",
                "strokeWidth": 1.5,
                "strokeDasharray": null
              }
            },
            "visible": true,
            "shape": "process",
            "zIndex": 4,
            "id": "602a3f85-c6bc-48db-9230-9cb402fdc6f0",
            "data": {
              "type": "tm.Process",
              "name": "Redirect URL",
              "description": "Enables users to resolve short URLs and be redirected to the corresponding long URLs via a dedicated API.",
              "outOfScope": false,
              "reasonOutOfScope": "",
              "hasOpenThreats": false,
              "handlesCardPayment": false,
              "handlesGoodsOrServices": false,
              "isWebApplication": false,
              "privilegeLevel": "",
              "threats": []
            }
          },
          {
            "position": {
              "x": 745,
              "y": 120
            },
            "size": {
              "width": 110,
              "height": 100
            },
            "attrs": {
              "text": {
                "text": "Shorten URL"
              },
              "body": {
                "stroke": "#333333",
                "strokeWidth": 1.5,
                "strokeDasharray": null
              }
            },
            "visible": true,
            "shape": "process",
            "zIndex": 5,
            "id": "1f9260a0-bd64-49d7-a839-58e5e43948dc",
            "data": {
              "type": "tm.Process",
              "name": "Shorten URL",
              "description": "Allows users to submit long URLs and receive shortened URLs via a dedicated API.",
              "outOfScope": false,
              "reasonOutOfScope": "",
              "hasOpenThreats": false,
              "handlesCardPayment": false,
              "handlesGoodsOrServices": false,
              "isWebApplication": false,
              "privilegeLevel": "",
              "threats": []
            }
          },
          {
            "position": {
              "x": 934.9999999999993,
              "y": 215
            },
            "size": {
              "width": 120,
              "height": 60
            },
            "attrs": {
              "text": {
                "text": "URL Mappings Database"
              },
              "topLine": {
                "stroke": "red",
                "strokeWidth": 2.5,
                "strokeDasharray": null
              },
              "bottomLine": {
                "stroke": "red",
                "strokeWidth": 2.5,
                "strokeDasharray": null
              }
            },
            "visible": true,
            "shape": "store",
            "zIndex": 6,
            "id": "afe966da-e79b-4415-8c3b-c8b7f3bfdb1c",
            "data": {
              "type": "tm.Store",
              "name": "URL Mappings Database",
              "description": "Data store containing the mappings between short URLs and their corresponding long URLs.\n\nDATA STORED: Long URL, Short URL, UserID, CreationDate",
              "outOfScope": false,
              "reasonOutOfScope": "",
              "hasOpenThreats": true,
              "isALog": false,
              "isEncrypted": false,
              "isSigned": false,
              "storesCredentials": false,
              "storesInventory": false,
              "threats": [
                {
                  "id": "05870dc9-0238-46d6-9f7f-356ba2ccf2f7",
                  "title": "Injection of malitious links as target URLs",
                  "status": "Open",
                  "severity": "Medium",
                  "type": "Tampering",
                  "description": "A malitious actor could inject malitious links as target URLs directly to database if the API Server auth is bypassed",
                  "mitigation": "Implement additional integrity checks in Database by introducing new field with entry's hash. ",
                  "modelType": "STRIDE",
                  "new": false,
                  "number": 15,
                  "score": ""
                },
                {
                  "id": "13081612-95c2-4bc6-a434-23f80a722d5b",
                  "title": "User's can modify other user's database entries ",
                  "status": "Open",
                  "severity": "Medium",
                  "type": "Tampering",
                  "description": "Other user's keys can be used to manage other user's records without RBAC in place. ",
                  "mitigation": "Implement Role-Based Access Control (RBAC) and Least Privilege by limitting API key permissions to only the necessary actions for the specific client or service.",
                  "modelType": "STRIDE",
                  "new": false,
                  "number": 16,
                  "score": ""
                },
                {
                  "id": "08f9abc9-fefb-48d0-9df5-061800a8cfdd",
                  "title": "No database access Logging in place",
                  "status": "Open",
                  "severity": "Low",
                  "type": "Repudiation",
                  "description": "Lack of the informations about how, when and who modified database entry. ",
                  "mitigation": "Enable Database Access Logging",
                  "modelType": "STRIDE",
                  "new": false,
                  "number": 28,
                  "score": ""
                }
              ]
            }
          },
          {
            "position": {
              "x": 902.4999999999993,
              "y": 470
            },
            "size": {
              "width": 112.5,
              "height": 60
            },
            "attrs": {
              "text": {
                "text": "Original URL"
              },
              "body": {
                "stroke": "#333333",
                "strokeWidth": 1.5,
                "strokeDasharray": "4 3"
              }
            },
            "visible": true,
            "shape": "actor",
            "zIndex": 7,
            "id": "2c0500fb-85fa-4497-908a-61b1ea2e09f4",
            "data": {
              "type": "tm.Actor",
              "name": "Original URL",
              "description": "Destination server of the original URL",
              "outOfScope": true,
              "reasonOutOfScope": "Original URL not in scope of URL shortener application",
              "hasOpenThreats": false,
              "providesAuthentication": false,
              "threats": []
            }
          },
          {
            "position": {
              "x": 507,
              "y": 237
            },
            "size": {
              "width": 100,
              "height": 100
            },
            "attrs": {
              "text": {
                "text": "API Server"
              },
              "body": {
                "stroke": "red",
                "strokeWidth": 2.5,
                "strokeDasharray": null
              }
            },
            "visible": true,
            "shape": "process",
            "zIndex": 8,
            "id": "23c4d6cc-6e67-47cd-855d-610b8e390d5f",
            "data": {
              "type": "tm.Process",
              "name": "API Server",
              "description": "The API Server is the central component of the URL Shortener Service. It manages all interactions with users and external services, handling requests for both shortening URLs and redirecting from short URLs to their original long URLs. ",
              "outOfScope": false,
              "reasonOutOfScope": "",
              "hasOpenThreats": true,
              "handlesCardPayment": false,
              "handlesGoodsOrServices": false,
              "isWebApplication": false,
              "privilegeLevel": "",
              "threats": [
                {
                  "id": "768bed9f-46a0-45e2-8274-e81a39d7d257",
                  "title": "Server overload from a high volume of requests",
                  "status": "Open",
                  "severity": "High",
                  "type": "Denial of service",
                  "description": "Server is prone to DoS and DDoS attacks if malitious actor decides to send large number of requests to API Server",
                  "mitigation": "Implement rate limiting and thorttling on the API to limit the number of requests per minute. Use firewalls and DDoS protection mechanisms like IP Whitelisting and Geo-Restrictions. ",
                  "modelType": "STRIDE",
                  "new": false,
                  "number": 20,
                  "score": ""
                },
                {
                  "id": "5855e886-4848-4474-b503-4f987e98d642",
                  "title": "Injection and Data Corruption",
                  "status": "Open",
                  "severity": "High",
                  "type": "Tampering",
                  "description": "Malitious actor can send unexpected or harmful data in API requests. When an API accepts data without validating its structure and format, malformed or incorrect data can end up in the database, leading to data integrity issues.",
                  "mitigation": "Implement request body validation sanitization and format checks to accept only valid data.",
                  "modelType": "STRIDE",
                  "new": false,
                  "number": 21,
                  "score": ""
                },
                {
                  "id": "4a44abbc-8717-4989-a51a-43af009b726d",
                  "title": "Server Errors due to Invalid Data",
                  "status": "Open",
                  "severity": "Medium",
                  "type": "Denial of service",
                  "description": "Unvalidated or improperly formatted data can cause exceptions or errors when processed by the server. Attackers could send requests with extremely large or deeply nested payloads, consuming excessive server resources during parsing or processing.",
                  "mitigation": "Implementing request body validations, sanitizations, limits.",
                  "modelType": "STRIDE",
                  "new": false,
                  "number": 22,
                  "score": ""
                },
                {
                  "id": "70520ef3-bed2-48a9-907f-7c4507521d96",
                  "title": "Bruteforce",
                  "status": "Open",
                  "severity": "Medium",
                  "type": "Spoofing",
                  "description": "Attackers could attempt to guess the API Key by sending multiple requests to an API Server. ",
                  "mitigation": "Ensure that API keys are sufficiently long and difficult to guess. Implement Rate Limiting and Throttling",
                  "modelType": "STRIDE",
                  "new": false,
                  "number": 23,
                  "score": ""
                },
                {
                  "id": "594cb38e-8357-4b27-9f8d-5f99a1c510bb",
                  "title": "API Key stored insecurily on client side",
                  "status": "Open",
                  "severity": "High",
                  "type": "Spoofing",
                  "description": "If the API Key is not stored securily on the client side it can be prone to leackage and utilization by malitious actors to gain access to the system. ",
                  "mitigation": "Issue short-lived access tokens instead of long-lasting API keys. Use OAuth2.0 and JWTs that expire after a short period. This reduces the window of time during which a compromised token can be used. Attackers will need to continually re-obtain new tokens, which can be difficult if proper authentication mechanisms are in place. Implement Role-Based Access Control (RBAC) and Least Privilege. Ensure you can quickly revoke or rotate API keys/tokens if they are suspected to be compromised.",
                  "modelType": "STRIDE",
                  "new": false,
                  "number": 24,
                  "score": ""
                },
                {
                  "id": "53e97aac-f730-4c49-919f-8f3095ae97f7",
                  "title": "API Key Leakage in transit",
                  "status": "Open",
                  "severity": "High",
                  "type": "Spoofing",
                  "description": "A MITM attack can be executed to retrieve the value of API Key if the data encryption in transit is not implemented",
                  "mitigation": "Ensure data in transit encryption by implementing TLS.",
                  "modelType": "STRIDE",
                  "new": false,
                  "number": 25,
                  "score": ""
                },
                {
                  "id": "e35ebddd-af1f-40c1-973e-4398ff38cb57",
                  "title": "Lack of request logging",
                  "status": "Open",
                  "severity": "Low",
                  "type": "Repudiation",
                  "description": "Users may deny performing certain operations (e.g., creating a redirect)",
                  "mitigation": "Log all operations related to users, such as creating and deleting URLs, and verify operations.",
                  "modelType": "STRIDE",
                  "new": false,
                  "number": 26,
                  "score": ""
                },
                {
                  "id": "fd52d1ec-367d-486c-b21f-eaade87fb2d3",
                  "title": "Attacker can read all resources",
                  "status": "Open",
                  "severity": "High",
                  "type": "Information disclosure",
                  "description": "By lack of RBAC attacker can manage all database entries using the single API Key",
                  "mitigation": "Implement Role-Based Access Control (RBAC) and Least Privilege",
                  "modelType": "STRIDE",
                  "new": false,
                  "number": 27,
                  "score": ""
                }
              ]
            }
          },
          {
            "position": {
              "x": 497,
              "y": 100
            },
            "size": {
              "width": 120,
              "height": 60
            },
            "attrs": {
              "text": {
                "text": "Hashed API keys"
              },
              "topLine": {
                "stroke": "red",
                "strokeWidth": 2.5,
                "strokeDasharray": null
              },
              "bottomLine": {
                "stroke": "red",
                "strokeWidth": 2.5,
                "strokeDasharray": null
              }
            },
            "visible": true,
            "shape": "store",
            "zIndex": 9,
            "id": "dd3ca2fb-9929-4ad2-bd6d-ec06b824924a",
            "data": {
              "type": "tm.Store",
              "name": "Hashed API keys",
              "description": "Database containing hashed API keys for authentication purposes.\n\nDATA STORED: Hashed API Key, UserID",
              "outOfScope": false,
              "reasonOutOfScope": "",
              "hasOpenThreats": true,
              "isALog": false,
              "isEncrypted": false,
              "isSigned": false,
              "storesCredentials": true,
              "storesInventory": false,
              "threats": [
                {
                  "id": "514bdf74-7f63-40e7-a711-793b427a736d",
                  "title": "No database access Logging in place",
                  "status": "Open",
                  "severity": "Low",
                  "type": "Repudiation",
                  "description": "Lack of the informations about how, when and who modified database entry. ",
                  "mitigation": "Enable Database Access Logging",
                  "modelType": "STRIDE",
                  "new": false,
                  "number": 29,
                  "score": ""
                },
                {
                  "id": "378c2ac3-e71e-45f4-bc21-263d6e946e2e",
                  "title": "Database data could leak due to misconfiguration",
                  "status": "Open",
                  "severity": "Low",
                  "type": "Tampering",
                  "description": "If database instance or its auth is misconfigured hashed API Keys could leak",
                  "mitigation": "Encrypt API keys and other sensitive data in the database. Ensure that database access is restricted to authorized components/users only. ",
                  "modelType": "STRIDE",
                  "new": false,
                  "number": 31,
                  "score": ""
                },
                {
                  "id": "7cabe452-0db3-47da-a3dc-b63b879996f0",
                  "title": "Hash collisions due to weak function",
                  "status": "Open",
                  "severity": "Medium",
                  "type": "Information disclosure",
                  "description": "If a weak hashing function (e.g., MD5 or SHA-1) is used, an attacker could potentially generate collisions or alter data without detection. Weak hashing functions are more vulnerable to bruteforce or rainbow table attacks, which allow attackers to more easily reverse or guess the hashed values of API Keys.",
                  "mitigation": "Replace weak hash functions like MD5 or SHA-1 with stronger, modern alternatives, such as SHA-256 or SHA-3.",
                  "modelType": "STRIDE",
                  "new": false,
                  "number": 32,
                  "score": ""
                }
              ]
            }
          },
          {
            "shape": "flow",
            "attrs": {
              "line": {
                "stroke": "#333333",
                "targetMarker": {
                  "name": "block"
                },
                "sourceMarker": {
                  "name": ""
                },
                "strokeDasharray": null
              }
            },
            "width": 200,
            "height": 100,
            "zIndex": 10,
            "connector": "smooth",
            "data": {
              "type": "tm.Flow",
              "name": "Store URL Mapping",
              "description": "The API Server processes the request for shortening a URL, generates a short URL, and stores the mapping between the short URL and the long URL in the URL Database.\n\nDATA EXCHANGED: Short URL, Long URL",
              "outOfScope": false,
              "reasonOutOfScope": "",
              "hasOpenThreats": false,
              "isBidirectional": false,
              "isEncrypted": false,
              "isPublicNetwork": false,
              "protocol": "",
              "threats": []
            },
            "id": "0bcd6bca-360b-4f4e-a505-187195135022",
            "labels": [
              "Store URL Mapping"
            ],
            "source": {
              "cell": "1f9260a0-bd64-49d7-a839-58e5e43948dc"
            },
            "target": {
              "cell": "afe966da-e79b-4415-8c3b-c8b7f3bfdb1c"
            },
            "vertices": [
              {
                "x": 960,
                "y": 150
              }
            ]
          },
          {
            "shape": "flow",
            "attrs": {
              "line": {
                "stroke": "#333333",
                "targetMarker": {
                  "name": "block"
                },
                "sourceMarker": {
                  "name": "block"
                },
                "strokeDasharray": null
              }
            },
            "width": 200,
            "height": 100,
            "zIndex": 10,
            "connector": "smooth",
            "data": {
              "type": "tm.Flow",
              "name": "Shorten Request",
              "description": "The user submits a long URL to the API for shortening.\n\nDATA EXCHANGED: Short URL, Long URL, UserID",
              "outOfScope": false,
              "reasonOutOfScope": "",
              "hasOpenThreats": false,
              "isBidirectional": true,
              "isEncrypted": false,
              "isPublicNetwork": false,
              "protocol": "",
              "threats": []
            },
            "id": "e8d0a24f-858a-45bd-b447-06e07897128a",
            "labels": [
              "Shorten Request"
            ],
            "source": {
              "cell": "23c4d6cc-6e67-47cd-855d-610b8e390d5f"
            },
            "target": {
              "cell": "1f9260a0-bd64-49d7-a839-58e5e43948dc"
            },
            "vertices": [
              {
                "x": 710,
                "y": 240
              }
            ]
          },
          {
            "shape": "flow",
            "attrs": {
              "line": {
                "stroke": "#333333",
                "targetMarker": {
                  "name": "block"
                },
                "sourceMarker": {
                  "name": "block"
                },
                "strokeDasharray": null
              }
            },
            "width": 200,
            "height": 100,
            "zIndex": 10,
            "connector": "smooth",
            "data": {
              "type": "tm.Flow",
              "name": "Redirect Request",
              "description": "The user submits a short URL to the API and gets redirected to the original Long URL.\n\nDATA EXCHANGED: Short URL, Long URL",
              "outOfScope": false,
              "reasonOutOfScope": "",
              "hasOpenThreats": false,
              "isBidirectional": true,
              "isEncrypted": false,
              "isPublicNetwork": false,
              "protocol": "",
              "threats": []
            },
            "id": "c01e0e5d-2f52-4b05-a659-58b854fb8b54",
            "labels": [
              "Redirect Request"
            ],
            "source": {
              "cell": "23c4d6cc-6e67-47cd-855d-610b8e390d5f"
            },
            "target": {
              "cell": "602a3f85-c6bc-48db-9230-9cb402fdc6f0"
            },
            "vertices": [
              {
                "x": 640,
                "y": 380
              }
            ]
          },
          {
            "shape": "flow",
            "attrs": {
              "line": {
                "stroke": "#333333",
                "targetMarker": {
                  "name": "block"
                },
                "sourceMarker": {
                  "name": ""
                },
                "strokeDasharray": null
              }
            },
            "width": 200,
            "height": 100,
            "zIndex": 10,
            "connector": "smooth",
            "data": {
              "type": "tm.Flow",
              "name": "Redirect User to URL",
              "description": "The user is redirected to the Long URL.",
              "outOfScope": false,
              "reasonOutOfScope": "",
              "hasOpenThreats": false,
              "isBidirectional": false,
              "isEncrypted": false,
              "isPublicNetwork": false,
              "protocol": "",
              "threats": []
            },
            "id": "07f08d6d-e984-4d14-9d25-36ad24b230bd",
            "labels": [
              "Redirect User to URL"
            ],
            "source": {
              "cell": "602a3f85-c6bc-48db-9230-9cb402fdc6f0"
            },
            "target": {
              "x": 950,
              "y": 470
            },
            "vertices": [
              {
                "x": 930,
                "y": 420
              }
            ]
          },
          {
            "shape": "flow",
            "attrs": {
              "line": {
                "stroke": "#333333",
                "targetMarker": {
                  "name": "block"
                },
                "sourceMarker": {
                  "name": ""
                },
                "strokeDasharray": null
              }
            },
            "width": 200,
            "height": 100,
            "zIndex": 10,
            "connector": "smooth",
            "data": {
              "type": "tm.Flow",
              "name": "Fetch API credentials",
              "description": "Hashed API keys are pulled to authenticate the user before performing any operation.\n\nDATA EXCHANGED: Hashed API key",
              "outOfScope": false,
              "reasonOutOfScope": "",
              "hasOpenThreats": false,
              "isBidirectional": false,
              "isEncrypted": false,
              "isPublicNetwork": false,
              "protocol": "",
              "threats": []
            },
            "id": "64b5c059-2c27-49ef-84e8-7e8ee050931f",
            "labels": [
              "Fetch API credentials"
            ],
            "source": {
              "cell": "23c4d6cc-6e67-47cd-855d-610b8e390d5f"
            },
            "target": {
              "cell": "dd3ca2fb-9929-4ad2-bd6d-ec06b824924a"
            }
          },
          {
            "shape": "flow",
            "attrs": {
              "line": {
                "stroke": "#333333",
                "targetMarker": {
                  "name": "block"
                },
                "sourceMarker": {
                  "name": "block"
                },
                "strokeDasharray": null
              }
            },
            "width": 200,
            "height": 100,
            "zIndex": 10,
            "connector": "smooth",
            "data": {
              "type": "tm.Flow",
              "name": "User Request",
              "description": "The User sends a request to the API Server to shorten a long URL or to get the redirect URL.\n\nDATA EXCHANGED: Long URL, Short URL, API key",
              "outOfScope": false,
              "reasonOutOfScope": "",
              "hasOpenThreats": false,
              "isBidirectional": true,
              "isEncrypted": false,
              "isPublicNetwork": false,
              "protocol": "",
              "threats": []
            },
            "id": "d6f0c600-c203-43af-80a3-3f9efb740b3e",
            "labels": [
              "User Request"
            ],
            "source": {
              "cell": "3ebe0ef2-2820-4e4d-8eb4-184714e6cf67"
            },
            "target": {
              "cell": "23c4d6cc-6e67-47cd-855d-610b8e390d5f"
            },
            "vertices": [
              {
                "x": 275,
                "y": 310
              },
              {
                "x": 370,
                "y": 310
              }
            ]
          },
          {
            "shape": "flow",
            "attrs": {
              "line": {
                "stroke": "#333333",
                "targetMarker": {
                  "name": "block"
                },
                "sourceMarker": {
                  "name": ""
                },
                "strokeDasharray": null
              }
            },
            "width": 200,
            "height": 100,
            "zIndex": 10,
            "connector": "smooth",
            "data": {
              "type": "tm.Flow",
              "name": "Retrieve Long URL",
              "description": "Long URL mapping is pulled from the database in order to redirect user.\n\nDATA EXCHANGED: Short URL, Long URL, UserID",
              "outOfScope": false,
              "reasonOutOfScope": "",
              "hasOpenThreats": false,
              "isBidirectional": false,
              "isEncrypted": false,
              "isPublicNetwork": false,
              "protocol": "",
              "threats": []
            },
            "id": "23e310de-2c36-4478-85d2-4999137f6df3",
            "labels": [
              "Retrieve Long URL"
            ],
            "source": {
              "cell": "602a3f85-c6bc-48db-9230-9cb402fdc6f0"
            },
            "target": {
              "cell": "afe966da-e79b-4415-8c3b-c8b7f3bfdb1c"
            },
            "vertices": [
              {
                "x": 970,
                "y": 320
              }
            ]
          }
        ]
      }
    ],
    "diagramTop": 1,
    "reviewer": "",
    "threatTop": 32
  }
}